finix/__init__.py
finix/api_client.py
finix/configuration.py
finix/exceptions.py
finix/model_utils.py
finix/rest.py
finix/schemas.py
finix/api/__init__.py
finix/api/authorizations_api.py
finix/api/balance_transfers_api.py
finix/api/compliance_forms_api.py
finix/api/devices_api.py
finix/api/disputes_api.py
finix/api/fee_profiles_api.py
finix/api/files_api.py
finix/api/identities_api.py
finix/api/instrument_updates_api.py
finix/api/merchant_profiles_api.py
finix/api/merchants_api.py
finix/api/onboarding_forms_api.py
finix/api/payment_instruments_api.py
finix/api/payout_profiles_api.py
finix/api/settlements_api.py
finix/api/split_transfers_api.py
finix/api/transfers_api.py
finix/api/verifications_api.py
finix/api/webhooks_api.py
finix/model/__init__.py
finix/model/accept_dispute.py
finix/model/additional_buyer_charges.py
finix/model/additional_healthcare_data.py
finix/model/additional_purchase_data.py
finix/model/additional_purchase_data_item_data.py
finix/model/additional_purchase_data_order_date.py
finix/model/address.py
finix/model/adjustment_transfers_list.py
finix/model/adjustment_transfers_list_embedded.py
finix/model/apple_pay_session.py
finix/model/apple_pay_session_request.py
finix/model/application.py
finix/model/application_links.py
finix/model/application_links_authorizations.py
finix/model/application_links_self.py
finix/model/application_profile.py
finix/model/application_profile_links.py
finix/model/application_profile_links_application.py
finix/model/application_profiles_list.py
finix/model/application_profiles_list_embedded.py
finix/model/applications_list.py
finix/model/applications_list_embedded.py
finix/model/associated_identity.py
finix/model/associated_identity_entity.py
finix/model/authorization.py
finix/model/authorization_captured.py
finix/model/authorization_captured_external_responses.py
finix/model/authorization_links.py
finix/model/authorization_links_device.py
finix/model/authorization_links_merchant_identity.py
finix-5.0.0.dist-info/LICENSE
finix-5.0.0.dist-info/METADATA
finix-5.0.0.dist-info/WHEEL
finix-5.0.0.dist-info/top_level.txt
finix-5.0.0.dist-info/RECORD
