Metadata-Version: 2.1
Name: finix
Version: 5.0.0
Summary: Finix API client library
Home-page: https://github.com/finix-payments/finix-python
Author: Finix
Author-email: support@finixpayments.com
License: Apache
Project-URL: Source Code, https://github.com/finix-payments/finix-python
Project-URL: Bug Tracker, https://github.com/finix-payments/finix-python/issues
Project-URL: Changes, https://github.com/finix-payments/finix-python/blob/main/CHANGELOG.md
Project-URL: Documentation, https://www.finix.com/docs
Keywords: Payment,Finix API
Requires-Python: >=3.6
License-File: LICENSE
Requires-Dist: urllib3 >=1.25.3
Requires-Dist: python-dateutil
